UnovaApi/Exceptions.py
UnovaApi/__init__.py
UnovaApi/adoption_data.csv
UnovaApi/drawCaptchas.py
UnovaApi/item_data.csv
UnovaApi/unoSession.py
UnovaApi/unova_api.py
UnovaApi/browser/__init__.py
UnovaApi/browser/chrome.exe
UnovaApi-0.1.3.dist-info/LICENSE
UnovaApi-0.1.3.dist-info/METADATA
UnovaApi-0.1.3.dist-info/WHEEL
UnovaApi-0.1.3.dist-info/top_level.txt
UnovaApi-0.1.3.dist-info/RECORD
