Metadata-Version: 2.1
Name: UnovaApi
Version: 0.1.3
Summary: Interface with Unovarpg with python
Home-page: https://github.com/Alexcmad/UnovaApi
Author: Alexander McIntosh
Author-email: mcintoshalexander80@gmail.com
Classifier: Programming Language :: Python :: 3
Classifier: License :: OSI Approved :: MIT License
Classifier: Operating System :: OS Independent
Requires-Python: >=3.7
License-File: LICENSE
Requires-Dist: beautifulsoup4 (==4.11.2)
Requires-Dist: lxml (==4.9.2)
Requires-Dist: pandas (==1.3.5)
Requires-Dist: Pillow (==9.4.0)
Requires-Dist: requests (==2.28.1)
Requires-Dist: selenium (==4.8.0)
Requires-Dist: TwoCaptcha (==0.0.1)
